<?xml version="1.0" encoding="windows-1256" ?>
<!DOCTYPE ViewLink SYSTEM "jbo_03_01.dtd">
<!---->
<ViewLink
  xmlns="http://xmlns.oracle.com/bc4j"
  Name="SpecialPlannersDocsFkVL"
  Version="12.2.1.9.14"
  InheritPersonalization="merge"
  EntityAssociation="gov.makkah.model.ass.SpecialPlannersDocsFkASS">
  <ViewLinkDefEnd
    Name="SpecialPlannersInfo"
    Cardinality="1"
    Source="true"
    Owner="gov.makkah.model.vo.SpecialPlannersInfoVO">
    <DesignTime>
      <Attr Name="_isUpdateable" Value="true"/>
      <Attr Name="_minCardinality" Value="1"/>
      <Attr Name="_finderName" Value="SpecialPlannersInfo"/>
    </DesignTime>
    <AttrArray Name="Attributes">
      <Item Value="gov.makkah.model.vo.SpecialPlannersInfoVO.DocId"/>
    </AttrArray>
  </ViewLinkDefEnd>
  <ViewLinkDefEnd
    Name="SpecialPlannersDocs"
    Cardinality="-1"
    Owner="gov.makkah.model.vo.SpecialPlannersDocsVO">
    <DesignTime>
      <Attr Name="_isUpdateable" Value="true"/>
      <Attr Name="_finderName" Value="SpecialPlannersDocs"/>
    </DesignTime>
    <AttrArray Name="Attributes">
      <Item Value="gov.makkah.model.vo.SpecialPlannersDocsVO.DocId"/>
    </AttrArray>
  </ViewLinkDefEnd>
</ViewLink>
